setup.py
bin/uttt_irc
uttt_irc/__init__.py
uttt_irc.egg-info/PKG-INFO
uttt_irc.egg-info/SOURCES.txt
uttt_irc.egg-info/dependency_links.txt
uttt_irc.egg-info/not-zip-safe
uttt_irc.egg-info/requires.txt
uttt_irc.egg-info/top_level.txt