Metadata-Version: 1.0
Name: uttt-irc
Version: 0.1-3
Summary: An IRC bot using the uttt package
Home-page: http://github.com/projectdelphai/uttt_irc
Author: projectdelphai
Author-email: projectdelphai@gmail.com
License: MIT
Platform: UNKNOWN
